{
  "name": "Introduction to Psychology I / Cognitive and Biological",
  "lectureHours": {
    "hybrid": 1,
    "online": 2
  },
  "labStudioOthersHours": {
    "hybrid": 0,
    "faceToFace": 0
  },
  "credits": {
    "bilkent": 3,
    "ECTS": 5
  },
  "code": "PSYC 101",
  "sections": {
    "PSYC 101-001": {
      "instructor": "Michelle Marie Adams",
      "quota": "55 Mand. 0 Elect.",
      "total_quota": 55,
      "enrollment": {
        "mandatory": 0,
        "elective": 0
      },
      "schedule": [
        {
          "day": "Monday",
          "start": "10:30",
          "end": "11:20",
          "place": "T-173",
          "class": "Hybrid Lecture"
        },
        {
          "day": "Monday",
          "start": "11:30",
          "end": "12:20",
          "place": "T-173(S)",
          "class": "Hybrid Lecture"
        },
        {
          "day": "Wednesday",
          "start": "20:10",
          "end": "21:00",
          "place": "T-173",
          "class": "Online Only Lecture"
        },
        {
          "day": "Wednesday",
          "start": "21:10",
          "end": "22:00",
          "place": "T-173",
          "class": "Online Only Lecture"
        }
      ],
      "name": "PSYC 101-001"
    },
    "PSYC 101-002": {
      "instructor": "Burcu Ayşen Ürgen",
      "quota": "55 Mand. 0 Elect.",
      "total_quota": 55,
      "enrollment": {
        "mandatory": 0,
        "elective": 0
      },
      "schedule": [
        {
          "day": "Monday",
          "start": "10:30",
          "end": "11:20",
          "place": "T-172",
          "class": "Hybrid Lecture"
        },
        {
          "day": "Monday",
          "start": "11:30",
          "end": "12:20",
          "place": "T-172(S)",
          "class": "Hybrid Lecture"
        },
        {
          "day": "Wednesday",
          "start": "20:10",
          "end": "21:00",
          "place": "T-172",
          "class": "Online Only Lecture"
        },
        {
          "day": "Wednesday",
          "start": "21:10",
          "end": "22:00",
          "place": "T-172",
          "class": "Online Only Lecture"
        }
      ],
      "name": "PSYC 101-002"
    }
  }
}