{
  "name": "Designing with Digital Media",
  "lectureHours": {
    "hybrid": 0,
    "online": 0
  },
  "labStudioOthersHours": {
    "hybrid": 0,
    "faceToFace": 3
  },
  "credits": {
    "bilkent": 0,
    "ECTS": 3
  },
  "code": "ADA 134",
  "sections": {
    "ADA 134-001": {
      "instructor": "Staff",
      "quota": "25 Mand. 0 Elect.",
      "total_quota": 25,
      "enrollment": {
        "mandatory": 15,
        "elective": 0
      },
      "schedule": [
        {
          "day": "Friday",
          "start": "08:30",
          "end": "09:20",
          "place": "FF-217(S)",
          "class": "Face-to-Face Lab/Studio"
        },
        {
          "day": "Friday",
          "start": "09:30",
          "end": "10:20",
          "place": "FF-217",
          "class": "Face-to-Face Lab/Studio"
        },
        {
          "day": "Friday",
          "start": "10:30",
          "end": "11:20",
          "place": "FF-217",
          "class": "Face-to-Face Lab/Studio"
        },
        {
          "day": "Friday",
          "start": "11:30",
          "end": "12:20",
          "place": "FF-217",
          "class": "Face-to-Face Lab/Studio"
        }
      ],
      "name": "ADA 134-001"
    }
  }
}