{
  "name": "Graphic Design III",
  "lectureHours": {
    "hybrid": 1,
    "online": 1
  },
  "labStudioOthersHours": {
    "hybrid": 8,
    "faceToFace": 0
  },
  "credits": {
    "bilkent": 6,
    "ECTS": 8.5
  },
  "code": "GRA 301",
  "sections": {
    "GRA 301-001": {
      "instructor": "Ekin Kılıç Ezer",
      "quota": "10 Mand. 0 Elect.",
      "total_quota": 10,
      "enrollment": {
        "mandatory": 0,
        "elective": 0
      },
      "schedule": [
        {
          "start": "08:30",
          "end": "09:20",
          "place": "",
          "class": "Hybrid Lab/Studio/Others"
        },
        {
          "start": "09:30",
          "end": "10:20",
          "place": "",
          "class": "Hybrid Lab/Studio/Others"
        },
        {
          "start": "10:30",
          "end": "11:20",
          "place": "",
          "class": "Hybrid Lab/Studio/Others"
        },
        {
          "start": "11:30",
          "end": "12:20",
          "place": "",
          "class": "Hybrid Lecture"
        },
        {
          "start": "11:30",
          "end": "12:20",
          "place": "(FS)",
          "class": "Hybrid Lab/Studio/Others"
        },
        {
          "start": "13:30",
          "end": "14:20",
          "place": "",
          "class": "Hybrid Lab/Studio/Others"
        },
        {
          "start": "13:30",
          "end": "14:20",
          "place": "",
          "class": "Hybrid Lab/Studio/Others"
        },
        {
          "start": "14:30",
          "end": "15:20",
          "place": "",
          "class": "Hybrid Lab/Studio/Others"
        },
        {
          "start": "14:30",
          "end": "15:20",
          "place": "",
          "class": "Hybrid Lab/Studio/Others"
        },
        {
          "start": "15:30",
          "end": "16:20",
          "place": "",
          "class": "Hybrid Lab/Studio/Others"
        },
        {
          "start": "15:30",
          "end": "16:20",
          "place": "(FS)",
          "class": "Hybrid Lab/Studio/Others"
        },
        {
          "start": "21:10",
          "end": "22:00",
          "place": "",
          "class": "Online Only Lecture"
        }
      ],
      "name": "GRA 301-001"
    },
    "GRA 301-002": {
      "instructor": "Oğuz Akın",
      "quota": "10 Mand. 0 Elect.",
      "total_quota": 10,
      "enrollment": {
        "mandatory": 0,
        "elective": 0
      },
      "schedule": [
        {
          "start": "08:30",
          "end": "09:20",
          "place": "",
          "class": "Hybrid Lab/Studio/Others"
        },
        {
          "start": "09:30",
          "end": "10:20",
          "place": "",
          "class": "Hybrid Lab/Studio/Others"
        },
        {
          "start": "10:30",
          "end": "11:20",
          "place": "(FS)",
          "class": "Hybrid Lab/Studio/Others"
        },
        {
          "start": "11:30",
          "end": "12:20",
          "place": "",
          "class": "Hybrid Lecture"
        },
        {
          "start": "11:30",
          "end": "12:20",
          "place": "(FS)",
          "class": "Hybrid Lab/Studio/Others"
        },
        {
          "start": "13:30",
          "end": "14:20",
          "place": "",
          "class": "Hybrid Lab/Studio/Others"
        },
        {
          "start": "13:30",
          "end": "14:20",
          "place": "",
          "class": "Hybrid Lab/Studio/Others"
        },
        {
          "start": "14:30",
          "end": "15:20",
          "place": "",
          "class": "Hybrid Lab/Studio/Others"
        },
        {
          "start": "14:30",
          "end": "15:20",
          "place": "",
          "class": "Hybrid Lab/Studio/Others"
        },
        {
          "start": "15:30",
          "end": "16:20",
          "place": "",
          "class": "Hybrid Lab/Studio/Others"
        },
        {
          "start": "15:30",
          "end": "16:20",
          "place": "",
          "class": "Hybrid Lab/Studio/Others"
        },
        {
          "start": "21:10",
          "end": "22:00",
          "place": "",
          "class": "Online Only Lecture"
        }
      ],
      "name": "GRA 301-002"
    }
  }
}