{
  "name": "Cities, Monuments and Landscapes of Classical Anatolia",
  "lectureHours": {
    "hybrid": 0,
    "online": 3
  },
  "labStudioOthersHours": {
    "hybrid": 0,
    "faceToFace": 0
  },
  "credits": {
    "bilkent": 0,
    "ECTS": 3
  },
  "code": "HART 423",
  "sections": {
    "HART 423-001": {
      "instructor": "Julian Bennett",
      "quota": "25 Mand. or Elect.",
      "total_quota": 25,
      "enrollment": {
        "mandatory": 1,
        "elective": 0
      },
      "schedule": [
        {
          "day": "Wednesday",
          "start": "08:30",
          "end": "09:20",
          "place": "H-133B(S)",
          "class": "Face-to-Face Lecture"
        },
        {
          "day": "Wednesday",
          "start": "09:30",
          "end": "10:20",
          "place": "H-133B",
          "class": "Face-to-Face Lecture"
        },
        {
          "day": "Friday",
          "start": "13:30",
          "end": "14:20",
          "place": "H-133B",
          "class": "Face-to-Face Lecture"
        },
        {
          "day": "Friday",
          "start": "14:30",
          "end": "15:20",
          "place": "H-133B",
          "class": "Face-to-Face Lecture"
        }
      ],
      "name": "HART 423-001"
    }
  }
}